README.md
setup.py
hivesigner/__init__.py
hivesigner/client.py
hivesigner/defaults.py
hivesigner/mixins.py
hivesigner/operations.py
hivesigner/utils.py
hivesigner.egg-info/PKG-INFO
hivesigner.egg-info/SOURCES.txt
hivesigner.egg-info/dependency_links.txt
hivesigner.egg-info/requires.txt
hivesigner.egg-info/top_level.txt