Metadata-Version: 1.0
Name: hivesigner
Version: 0.1.0
Summary: Python client library of Hivesigner
Home-page: https://github.com/emre/hivesigner
Author: Emre Yilmaz
Author-email: mail@emreyilmaz.me
License: MIT
Platform: UNKNOWN
